<?xml version="1.0" encoding="utf-8"?>
<openerp>
    <data>
      <!-- Copyright (c) 2017-Present Webkul Software Pvt. Ltd. (<https://webkul.com/>) -->
      <!-- See LICENSE URL <https://store.webkul.com/license.html/> for full copyright and licensing details. -->
        <record id="channel_category_mappings_search" model="ir.ui.view">
            <field name="name">channel.category.mappings.search</field>
            <field name="model">channel.category.mappings</field>
            <field name="arch" type="xml">
            <search string="Channel Category Mappings" >
                 <field name="category_name"/>
                 <field name="store_category_id"/>

                 <group expand="0" string="Group By...">
                    <filter string="Channel" name="filter_by_ecom_store" context="{'group_by':'ecom_store'}"/>
                    <filter string="Instance" name="filter_by_channel_id" context="{'group_by':'channel_id'}"/>
                    <filter string="Need Update" name='need_sync'  domain="[]" context="{'group_by':'need_sync'}"/>
                    <group string='Filters'>
                        <filter icon="terp-check" name="ecom_store" string="Channel"
                            domain="[]" help="Channel" context="{'group_by':'ecom_store'}"/>
                            <filter icon="terp-check" name="channel_id" string="Instance"
                            domain="[]" help="Instance" context="{'group_by':'channel_id'}"/>
                    </group>

                 </group>
            </search>
            </field>
        </record>

        <record id="channel_category_mapping_form" model="ir.ui.view">
            <field name="name">channel.category.mappings.form</field>
            <field name="model">channel.category.mappings</field>
            <field name="type">form</field>
            <field name="arch" type="xml">
                <form >
                    <sheet>
                        <group>
                            <group>
                                <field name='channel_id'/>
                                <field name='ecom_store'/>
                            </group>
                            <group>
                                <field name='operation'/>
                                <field name="need_sync"/>
                            </group>
                        </group>
                        <group col="4">
                            <field name='store_category_id'/>
                            <field name="leaf_category"/>
                            <field name="category_name"/>
                            <field name="odoo_category_id" invisible="1"/>
                        </group>

                    </sheet>

                </form>
            </field>
        </record>


    	<record id="channel_category_mapping_tree" model="ir.ui.view">
            <field name="name">channel.category.mappings.tree</field>
            <field name="model">channel.category.mappings</field>
            <field name="type">tree</field>
            <field name="arch" type="xml">
                <tree string="Channel Category Mapping" decoration-danger="need_sync=='yes'">
                    <field name="channel_id"/>
                    <field name="store_category_id"/>
                    <field name="odoo_category_id"/>
                    <field name="category_name"/>
                    <field name="leaf_category"/>
                    <field name="create_date"/>
                    <field name="write_date"/>
                    <field name="need_sync"/>
                </tree>
            </field>
        </record>

        <record id="channel_category_mapping_action_id" model="ir.actions.act_window">
            <field name="name">Channel Category Mappings</field>
            <field name="res_model">channel.category.mappings</field>
            <field name="view_type">form</field>
            <field name="view_mode">tree,form</field>
            <field name="context">{"search_default_filter_by_ecom_store":1,"search_default_filter_by_channel_id":1}</field>
            <field name="view_id" ref="channel_category_mapping_tree"/>
        </record>


 	</data>
</openerp>
